odoo10_addon_product_weight-10.0.1.0.0-py2.7-nspkg.pth
odoo/addons/product_weight/README.rst
odoo/addons/product_weight/__init__.py
odoo/addons/product_weight/__manifest__.py
odoo/addons/product_weight/i18n/fr.po
odoo/addons/product_weight/i18n/product_weight.pot
odoo/addons/product_weight/models/__init__.py
odoo/addons/product_weight/models/bom.py
odoo/addons/product_weight/static/description/icon.png
odoo/addons/product_weight/tests/__init__.py
odoo/addons/product_weight/tests/test_compute_bom_weight.py
odoo/addons/product_weight/views/product_view.xml
odoo/addons/product_weight/wizard/__init__.py
odoo/addons/product_weight/wizard/product_weight_update.py
odoo/addons/product_weight/wizard/product_weight_update_view.xml
odoo10_addon_product_weight-10.0.1.0.0.dist-info/DESCRIPTION.rst
odoo10_addon_product_weight-10.0.1.0.0.dist-info/METADATA
odoo10_addon_product_weight-10.0.1.0.0.dist-info/RECORD
odoo10_addon_product_weight-10.0.1.0.0.dist-info/WHEEL
odoo10_addon_product_weight-10.0.1.0.0.dist-info/metadata.json
odoo10_addon_product_weight-10.0.1.0.0.dist-info/namespace_packages.txt
odoo10_addon_product_weight-10.0.1.0.0.dist-info/top_level.txt
